AUTHORS.rst
CONTRIBUTING.rst
HISTORY.rst
LICENSE
MANIFEST.in
README.rst
setup.cfg
setup.py
docs/Makefile
docs/authors.rst
docs/conf.py
docs/contributing.rst
docs/history.rst
docs/index.rst
docs/installation.rst
docs/make.bat
docs/readme.rst
docs/usage.rst
house_hunter/__init__.py
house_hunter/cli.py
house_hunter/house_hunter.py
house_hunter.egg-info/PKG-INFO
house_hunter.egg-info/SOURCES.txt
house_hunter.egg-info/dependency_links.txt
house_hunter.egg-info/entry_points.txt
house_hunter.egg-info/not-zip-safe
house_hunter.egg-info/requires.txt
house_hunter.egg-info/top_level.txt
tests/test_house_hunter.py