Metadata-Version: 1.1
Name: house-hunter
Version: 0.1.0
Summary: House Hunter contains methods to search popular housing websites
Home-page: https://github.com/rogersjw/house_hunter
Author: Jonathan Rogers
Author-email: Jonathan.W.Rogers@gmail.com
License: MIT license
Keywords: house_hunter
Platform: UNKNOWN
Classifier: Development Status :: 2 - Pre-Alpha
Classifier: Intended Audience :: Developers
Classifier: License :: OSI Approved :: MIT License
Classifier: Natural Language :: English
Classifier: Programming Language :: Python :: 2
Classifier: Programming Language :: Python :: 2.7
Classifier: Programming Language :: Python :: 3
Classifier: Programming Language :: Python :: 3.4
Classifier: Programming Language :: Python :: 3.5
Classifier: Programming Language :: Python :: 3.6
Classifier: Programming Language :: Python :: 3.7
